add_funtion_sum_and_sub/__init__.py
add_funtion_sum_and_sub/sub.py
add_funtion_sum_and_sub/sum.py
add_funtion_sum_and_sub-0.0.1.dist-info/LICENSE.TXT
add_funtion_sum_and_sub-0.0.1.dist-info/METADATA
add_funtion_sum_and_sub-0.0.1.dist-info/WHEEL
add_funtion_sum_and_sub-0.0.1.dist-info/top_level.txt
add_funtion_sum_and_sub-0.0.1.dist-info/RECORD
