Metadata-Version: 2.1
Name: add-funtion-sum-and-sub
Version: 0.0.1
Summary: add_funtion_sum_and_sub
Author: kurban hussain
Author-email: kurbanhussain086@gmail.com
Keywords: arithmetic,math,mathematics,python tutorial,kurban hussain,two number add module,sum,sub,number
Classifier: Development Status :: 1 - Planning
Classifier: Intended Audience :: Developers
Classifier: Programming Language :: Python :: 3
Classifier: Operating System :: Unix
Classifier: Operating System :: MacOS :: MacOS X
Classifier: Operating System :: Microsoft :: Windows
License-File: LICENSE.TXT
